Metadata-Version: 1.1
Name: mpu6050-raspberrypi
Version: 1.0.3.3
Summary: A Python module for accessing the MPU-6050 digital accelerometer and gyroscope on a Raspberry Pi.
Home-page: https://github.com/Tijndagamer/mpu6050
Author: MrTijn/Tijndagamer
Author-email: tijndagamer25@gmail.com
License: MIT
Keywords: mpu6050 raspberry
Platform: UNKNOWN
Classifier: License :: OSI Approved :: MIT License
Classifier: Topic :: Software Development :: Libraries
Classifier: Programming Language :: Python :: 2.7
